{
  "config": {
    "startX": 0,
    "startY": 0,
    "frameWidth": 180,
    "frameHeight": 300,
    "frameCount": 5,
    "fps": 10,
    "globalWidth": 350,
    "globalHeight": 350
  },
  "bgRemoval": {
    "enabled": true,
    "keyColor": "#ff00ff",
    "threshold": "37",
    "erode": "3"
  },
  "sourceFilename": "east.png",
  "anchorOverrides": {
    "0": {
      "x": 103.5,
      "y": 149
    },
    "1": {
      "x": 105.5,
      "y": 151
    },
    "2": {
      "x": 107.5,
      "y": 147
    },
    "3": {
      "x": 101.5,
      "y": 150
    },
    "4": {
      "x": 103.5,
      "y": 151
    }
  },
  "frameOverrides": {
    "0": {
      "x": 33,
      "y": 147
    },
    "1": {
      "x": 229,
      "y": 146
    },
    "2": {
      "x": 437,
      "y": 148
    },
    "3": {
      "x": 641,
      "y": 147
    },
    "4": {
      "x": 832,
      "y": 147
    }
  }
}